data_art/__init__.py
data_art/html_visualizer.py
data_art-0.0.13.dist-info/LICENSE.txt
data_art-0.0.13.dist-info/METADATA
data_art-0.0.13.dist-info/WHEEL
data_art-0.0.13.dist-info/top_level.txt
data_art-0.0.13.dist-info/RECORD
