Metadata-Version: 2.1
Name: data-art
Version: 0.0.13
Summary: Python dynamic and web friendly report generator
Home-page: https://github.com/erfanvaredi/data-art
Author: Erfan Varedi
Author-email: erfanvaredi@gmail.com
Project-URL: Bug Tracker, https://github.com/erfanvaredi/data-art/-/issues
Project-URL: repository, https://github.com/erfanvaredi/data-art
Classifier: Programming Language :: Python :: 3
Classifier: License :: OSI Approved :: MIT License
Classifier: Operating System :: OS Independent
Requires-Python: >=3.7
License-File: LICENSE.txt
